environmental/__init__.py
environmental/property_maker.py
environmental/safe_parser.py
environmental/safe_types.py
environmental-1.3.dist-info/DESCRIPTION.rst
environmental-1.3.dist-info/METADATA
environmental-1.3.dist-info/RECORD
environmental-1.3.dist-info/WHEEL
environmental-1.3.dist-info/metadata.json
environmental-1.3.dist-info/top_level.txt
