Metadata-Version: 2.0
Name: environmental
Version: 1.3
Summary: Map a python configuration from environment variables
Home-page: https://github.com/zalando/environmental
Author: Zalando SE
Author-email: UNKNOWN
License: Apache License Version 2.0
Platform: UNKNOWN
Classifier: Programming Language :: Python
Classifier: Programming Language :: Python :: 3
Classifier: Development Status :: 4 - Beta
Classifier: Intended Audience :: Developers
Classifier: Operating System :: OS Independent
Requires-Dist: typing
